agentCores/__init__.py
agentCores/__main__.py
agentCores/agentCores.py
agentCores/agentMatrix.py
agentCores/databaseManager.py
agentCores/researchAssistant.py
agentCores/data/agentCoresLogoFix.png
agentCores-0.2.4.dist-info/LICENSE
agentCores-0.2.4.dist-info/METADATA
agentCores-0.2.4.dist-info/WHEEL
agentCores-0.2.4.dist-info/top_level.txt
agentCores-0.2.4.dist-info/RECORD
