Metadata-Version: 2.1
Name: agentCores
Version: 0.2.4
Summary: A flexible framework for creating and managing AI agent configurations
Home-page: https://github.com/Leoleojames1/agentCores
Author: Leo Borcherding
License: MIT License
Project-URL: Homepage, https://github.com/Leoleojames1/agentCores
Project-URL: Issues, https://github.com/Leoleojames1/agentCores/issues
Keywords: ai,agents,llm,framework
Classifier: Programming Language :: Python :: 3
Classifier: License :: OSI Approved :: MIT License
Classifier: Operating System :: OS Independent
Requires-Python: >=3.8
License-File: LICENSE
Requires-Dist: pymongo
Requires-Dist: duckduckgo_search
